pkelambda/__init__.py
pkelambda/base.py
pkelambda/data_structures.py
pkelambda/langcodes.py
pkelambda/readers.py
pkelambda/utils.py
pkelambda/models/Kea-semeval2010.py2.pickle
pkelambda/models/Kea-semeval2010.py3.pickle
pkelambda/models/WINGNUS-semeval2010.py2.pickle
pkelambda/models/WINGNUS-semeval2010.py3.pickle
pkelambda/models/df-semeval2010.tsv.gz
pkelambda/models/lda-1000-semeval2010.py2.pickle.gz
pkelambda/models/lda-1000-semeval2010.py3.pickle.gz
pkelambda/supervised/__init__.py
pkelambda/supervised/api.py
pkelambda/supervised/feature_based/__init__.py
pkelambda/supervised/feature_based/kea.py
pkelambda/supervised/feature_based/topiccorank.py
pkelambda/supervised/feature_based/wingnus.py
pkelambda/supervised/neural_based/__init__.py
pkelambda/supervised/neural_based/seq2seq.py
pkelambda/unsupervised/__init__.py
pkelambda/unsupervised/graph_based/__init__.py
pkelambda/unsupervised/graph_based/collabrank.py
pkelambda/unsupervised/graph_based/expandrank.py
pkelambda/unsupervised/graph_based/multipartiterank.py
pkelambda/unsupervised/graph_based/positionrank.py
pkelambda/unsupervised/graph_based/single_tpr.py
pkelambda/unsupervised/graph_based/singlerank.py
pkelambda/unsupervised/graph_based/textrank.py
pkelambda/unsupervised/graph_based/topicrank.py
pkelambda/unsupervised/statistical/__init__.py
pkelambda/unsupervised/statistical/embedrank.py
pkelambda/unsupervised/statistical/firstphrases.py
pkelambda/unsupervised/statistical/kpminer.py
pkelambda/unsupervised/statistical/tfidf.py
pkelambda/unsupervised/statistical/yake.py
pkelambda-1.8.1.dist-info/LICENCE.md
pkelambda-1.8.1.dist-info/METADATA
pkelambda-1.8.1.dist-info/WHEEL
pkelambda-1.8.1.dist-info/top_level.txt
pkelambda-1.8.1.dist-info/RECORD
