Metadata-Version: 2.1
Name: pkelambda
Version: 1.8.1
Summary: Python Keyphrase Extraction module
Home-page: https://github.com/boudinfl/pke
Author: pkelambda contributors
Author-email: florian.boudin@univ-nantes.fr
License: gnu
Platform: UNKNOWN
License-File: LICENCE.md
Requires-Dist: nltk
Requires-Dist: networkx
Requires-Dist: numpy
Requires-Dist: scipy
Requires-Dist: spacy
Requires-Dist: six
Requires-Dist: sklearn
Requires-Dist: unidecode
Requires-Dist: future
Requires-Dist: joblib
